README.md
setup.py
pyaltt/__init__.py
pyaltt/f.py
pyaltt/supervisor.py
pyaltt/threads.py
pyaltt/workers.py
pyaltt.egg-info/PKG-INFO
pyaltt.egg-info/SOURCES.txt
pyaltt.egg-info/dependency_links.txt
pyaltt.egg-info/top_level.txt