Metadata-Version: 2.1
Name: pyaltt
Version: 0.2.7
Summary: Various tools for functions, looped and queued workers etc.
Home-page: https://github.com/alttch/pyaltt
Author: Altertech Group
Author-email: pr@altertech.com
License: Apache License 2.0
Platform: UNKNOWN
Classifier: Programming Language :: Python :: 3
Classifier: License :: OSI Approved :: Apache Software License
Classifier: Topic :: Software Development :: Libraries
